Metadata-Version: 1.0
Name: dsnd-prob-1
Version: 1.2
Summary: Gaussian & Binomial distributions
Home-page: UNKNOWN
Author: UNKNOWN
Author-email: UNKNOWN
License: UNKNOWN
Platform: UNKNOWN
